sift/__init__.py
sift/_backend_utils.py
sift/_constants.py
sift/_sift.py
sift/_types.py
sift/_utils.py
sift/kernels.py
sift_sc-0.1.0.dist-info/LICENSE
sift_sc-0.1.0.dist-info/WHEEL
sift_sc-0.1.0.dist-info/METADATA
sift_sc-0.1.0.dist-info/RECORD
