Metadata-Version: 2.1
Name: sift-sc
Version: 0.1.0
Summary: Biological signal filtering in single-cell data.
Home-page: https://github.com/nitzanlab/sift-sc
License: BSD-3-Clause
Author: Zoe Piran
Author-email: zoe.piran@mail.huji.ac.il
Requires-Python: >=3.8,<4.0
Classifier: Development Status :: 5 - Production/Stable
Classifier: Intended Audience :: Science/Research
Classifier: License :: OSI Approved :: BSD License
Classifier: Natural Language :: English
Classifier: Operating System :: MacOS :: MacOS X
Classifier: Operating System :: Microsoft :: Windows
Classifier: Operating System :: POSIX :: Linux
Classifier: Programming Language :: Python :: 3
Classifier: Programming Language :: Python :: 3.8
Classifier: Programming Language :: Python :: 3.9
Classifier: Programming Language :: Python :: 3.10
Classifier: Programming Language :: Python :: 3.11
Classifier: Programming Language :: Python :: 3.10
Classifier: Programming Language :: Python :: 3.8
Classifier: Programming Language :: Python :: 3.9
Classifier: Topic :: Scientific/Engineering :: Bio-Informatics
Provides-Extra: dev
Provides-Extra: docs
Provides-Extra: gpu
Provides-Extra: test
Requires-Dist: anndata (>=0.8)
Requires-Dist: furo (>=2022.04.07) ; extra == "docs"
Requires-Dist: ipython (>=7)
Requires-Dist: matplotlib (>=3.3)
Requires-Dist: nbsphinx (>=0.8) ; extra == "docs"
Requires-Dist: numpy (>=1.15)
Requires-Dist: pandas (>=1.3)
Requires-Dist: pre-commit (>=2.10) ; extra == "dev"
Requires-Dist: pykeops (>=2.0)
Requires-Dist: pytest (>=7) ; extra == "test"
Requires-Dist: rich (>=10)
Requires-Dist: scanpy (>=1.7)
Requires-Dist: scipy (>=1.5.0)
Requires-Dist: seaborn (>=0.10)
Requires-Dist: sphinx (>=4) ; extra == "docs"
Requires-Dist: sphinx-autodoc-typehints (>=1.12) ; extra == "docs"
Requires-Dist: sphinxcontrib-bibtex (>=2)
Requires-Dist: torch (>=1.8.0) ; extra == "gpu"
Project-URL: Documentation, https://sift-sc.readthedocs.io/
